boost2simple/__init__.py
boost2simple/cli.py
boost2simple/converter.py
boost2simple/gui.py
boost2simple/util.py
boost2simple/notes/__init__.py
boost2simple/notes/boostnote.py
boost2simple/notes/simplenote.py
boost2simple-1.2.0.dist-info/LICENSE
boost2simple-1.2.0.dist-info/METADATA
boost2simple-1.2.0.dist-info/WHEEL
boost2simple-1.2.0.dist-info/top_level.txt
boost2simple-1.2.0.dist-info/RECORD
