Metadata-Version: 2.1
Name: boost2simple
Version: 1.2.0
Summary: A script to convert BoostNote exports to SimpleNote export format
Home-page: https://github.com/RWitak/boost2simple
Author: Rafael Witak
Author-email: rafael.witak@gmail.com
License: UNKNOWN
Project-URL: Bug Tracker, https://github.com/RWitak/boost2simple/issues
Platform: UNKNOWN
Classifier: Programming Language :: Python :: 3
Classifier: License :: OSI Approved :: MIT License
Classifier: Operating System :: Microsoft :: Windows
Requires-Python: >=3.7
License-File: LICENSE
